llm_obfuscator/__init__.py
llm_obfuscator/cli.py
llm_obfuscator/main.py
llm_obfuscator/tokenizer/__init__.py
llm_obfuscator/tokenizer/base_tokenizer.py
llm_obfuscator/tokenizer/huggingface_tokenizer.py
llm_obfuscator/tokenizer/openai_tokenizer.py
llm_obfuscator/tokenizer/tokenizer.py
src/__init__.py
src/main.py
src/tokenizer/__init__.py
src/tokenizer/base_tokenizer.py
src/tokenizer/huggingface_tokenizer.py
src/tokenizer/openai_tokenizer.py
src/tokenizer/tokenizer.py
llm_obfuscator-0.1.0.dist-info/LICENSE
llm_obfuscator-0.1.0.dist-info/METADATA
llm_obfuscator-0.1.0.dist-info/WHEEL
llm_obfuscator-0.1.0.dist-info/entry_points.txt
llm_obfuscator-0.1.0.dist-info/top_level.txt
llm_obfuscator-0.1.0.dist-info/RECORD
