Metadata-Version: 2.2
Name: llm-obfuscator
Version: 0.1.0
Summary: A tool for obfuscating text by manipulating token IDs while preserving token count and structure
Home-page: https://github.com/yourusername/llm-obfusicator
Author: Alex
Author-email: your.email@example.com
Project-URL: Bug Reports, https://github.com/yourusername/llm-obfusicator/issues
Project-URL: Source, https://github.com/yourusername/llm-obfusicator
Keywords: llm,tokenization,obfuscation,nlp,ai
Classifier: Development Status :: 3 - Alpha
Classifier: Intended Audience :: Developers
Classifier: Intended Audience :: Science/Research
Classifier: License :: OSI Approved :: MIT License
Classifier: Programming Language :: Python :: 3
Classifier: Programming Language :: Python :: 3.8
Classifier: Programming Language :: Python :: 3.9
Classifier: Programming Language :: Python :: 3.10
Classifier: Topic :: Scientific/Engineering :: Artificial Intelligence
Classifier: Topic :: Text Processing
Requires-Python: >=3.8
License-File: LICENSE
Requires-Dist: tiktoken>=0.5.0
Requires-Dist: transformers>=4.30.0
Requires-Dist: numpy>=1.20.0
Dynamic: author
Dynamic: author-email
Dynamic: classifier
Dynamic: description
Dynamic: description-content-type
Dynamic: home-page
Dynamic: keywords
Dynamic: project-url
Dynamic: requires-dist
Dynamic: requires-python
Dynamic: summary
